jinjasimplecli/__init__.py
jinjasimplecli/cli.py
jinjasimplecli/extensions.py
jinjasimplecli/main.py
jinjasimplecli-1.0.7.dist-info/LICENSE
jinjasimplecli-1.0.7.dist-info/METADATA
jinjasimplecli-1.0.7.dist-info/WHEEL
jinjasimplecli-1.0.7.dist-info/entry_points.txt
jinjasimplecli-1.0.7.dist-info/top_level.txt
jinjasimplecli-1.0.7.dist-info/RECORD
