Metadata-Version: 2.1
Name: jinjasimplecli
Version: 1.0.7
Summary: Jinja Simple CLI, is a tool that allows you to compose and insert data in to templates, with support for template inheritance and global functions. It uses json files as input for the data, and it can handle templates from standard input.
Home-page: https://github.com/ekiim/jinjasimplecli
Author: Miguel Salgado
Author-email: me@ekiim.xyz
License: BSD
Keywords: jinja templates cli
Platform: UNKNOWN
Classifier: Development Status :: 4 - Beta
Classifier: Environment :: Console
Classifier: License :: OSI Approved :: BSD License
Classifier: Operating System :: OS Independent
Classifier: Programming Language :: Python :: 3
Classifier: Topic :: Text Processing
Requires-Dist: jinja2
